[
  {
    "id": 9,
    "title": "妥善運用資訊科技  營造以病人為中心的友善照護環境",
    "description": "文／護理部"
  }, 
  {
    "id": 8,
    "title": "生命意外旅程中的綠洲—門診化療室",
    "description": "文／護理部"
  }, 
  {
    "id": 7,
    "title": "救人第一  本院加護中心護理師見義勇為救助昏迷長者",
    "description": "文／編輯部  資料提供／護理部"
  },
  {
    "id": 6,
    "title": "本院於9月1日舉辦55週年院慶典禮(一)",
    "description": "文／編輯部  資料提供／總務室、人事室"
  },
  {
    "id": 5,
    "title": "本院於9月1日舉辦55週年院慶典禮(二)",
    "description": "文／編輯部  資料提供／總務室、人事室"
  },
  {
    "id": 4,
    "title": "走過感恩與成長的歲月  振興院童話當年",
    "description": "文／呂建和（客服中心高專）、吳佳真（編輯）"
  },
  {
    "id": 3,
    "title": "本院配合辦理2022年學齡前兒童整合性社區篩檢",
    "description": "文／醫療業務部"
  },
  {
    "id": 2,
    "title": "本院魏崢院長於農曆除夕及大年初一慰問值班人員",
    "description": "文／編輯部&nbsp&nbsp資料提供／總務室"
  },
  {
    "id": 1,
    "title": "走過廿五年&nbsp振興加護護理訓練疫情下順利結訓",
    "description": "文/護理部"
  }
]